Workbook

Sheet Summary
B2: Foreign Outflows, Domestic Inflows and the Indian Equity Market
B3: FPI and DII equity flows, SIP growth and macro conditions, January 2017 to September 2026 (117 monthly observations)
B4: Status: preliminary. FPI and DII series are from different sources and are being rebuilt on one NSE basis. October 2026 excluded as a partial month.
B6: Complete months analysed | F6: FPI-selling months fully offset | J6: Growth in monthly SIP contributions
B7: =COUNT('Monthly Data'!$A$5:$A$121) -> 117 | F7: ='Offset Analysis'!B10 -> 0.79245283 | J7: ='Monthly Data'!L121/'Monthly Data'!L5 -> 7.9340659
B8: Jan 2017 to Sep 2026 | F8: ='Offset Analysis'!B7&" of "&'Offset Analysis'!B6&" months" -> 42 of 53 months | J8: ₹4,095 cr to ₹32,490 cr
B10: Key findings
B11: Domestic buying usually covers foreign selling | F11: DII buying exceeded FPI selling in 42 of 53 selling months, and in 18 of 19 since 2024.
B12: Offsetting does not mean a rising market | F12: Fully offset months still averaged a -1.33% Nifty return, against +2.61% in months without FPI selling.
B13: Large outflows are harder to absorb | F13: In the ten biggest outflow months, 6 were fully offset and the average Nifty return was -3.95%.
B14: The domestic savings base has grown about eightfold | F14: Monthly SIPs rose from ₹4,095 cr to ₹32,490 cr; equity mutual fund AUM rose about sevenfold.
B15: The rupee is the macro variable that matters most | F15: USD/INR monthly change correlates -0.52 with Nifty returns; repo rate and CPI show almost none.
B17: Charts
B50: Source: NSDL, Trendlyne, NSE, AMFI, RBI. Detailed method and limitations are on the Method & Sources tab.

Sheet Findings
A1: Research findings
A2: Figures are preliminary (see status note on Summary). Live values are on the Offset Analysis and Correlations tabs.
A4: # | B4: Question | C4: Result | D4: Reading | E4: Limitation
A5: 1 | B5: Do domestic institutions absorb foreign selling? | C5: FPI was a net seller in 53 of 117 complete months. DII buying exceeded the selling in 42 of them (79%). Since January 2024 the figure is 18 of 19. | D5: Domestic buying has regularly been large enough to cover foreign selling, and more so in recent years. | E5: Net monthly flows only. Says nothing about intra-month timing, and FPI and DII data are not yet from one source.
A6: 2 | B6: Does offsetting protect the market? | C6: Average Nifty return in FPI-selling months was -1.08%. Fully offset months averaged -1.33%; months not fully offset averaged -0.16%; months without FPI selling averaged +2.61%. | D6: Offsetting did not coincide with positive returns. Domestic buying absorbs selling but does not prevent weak months. | E6: Group averages are not causal. Whatever drives foreign selling may also drive domestic buying and returns.
A7: 3 | B7: Are the largest outflow months harder to offset? | C7: Of the ten largest FPI-selling months, 6 were fully offset and the average Nifty return was -3.95%. Across the other 43 selling months, 84% were fully offset and the average return was -0.39%. | D7: Offset rate falls and returns weaken when foreign selling is very large. | E7: Ten observations. Treat as indicative.
A8: 4 | B8: Is the domestic savings base growing? | C8: Monthly SIP contributions rose from ₹4,095 crore (Jan 2017) to ₹32,490 crore (Sep 2026), about 7.9 times. Equity mutual fund AUM rose from ₹5.4 lakh crore (Mar 2017) to ₹37.9 lakh crore (Jun 2026), about 7 times. | D8: Retail participation through SIPs has expanded steadily, which supports the case for a larger domestic buffer. | E8: AUM growth includes market appreciation. SIP figures are gross contributions, not net equity purchases.
A9: 5 | B9: Is SIP growth linked to offsetting? | C9: Across FPI-selling months, the correlation between SIP level and full offset is +0.26; with the offset ratio it is -0.04. | D9: SIP growth is modestly associated with the chance of a full offset but not with its size. | E9: Both series trend upward over time, so the link may reflect time rather than a direct relationship.
A10: 6 | B10: How do flows relate to returns? | C10: Same-month correlation with Nifty return: FPI +0.53, DII -0.47, combined +0.07. | D10: Foreign flows move with the market. Domestic flows move against it, consistent with buying into weakness. | E10: Contemporaneous correlation. Direction of cause is not established.
A11: 7 | B11: Do macro variables matter? | C11: USD/INR monthly change vs Nifty return: r = -0.52 (107 months), -0.37 after trimming extremes, and between -0.39 and -0.66 in each sub-period. Repo rate (-0.06) and CPI (+0.03) show almost no relationship with returns. | D11: Rupee weakness is the macro variable most consistently associated with weak equity months in this sample. | E11: Association only. The rupee and equity prices respond to common drivers such as global risk sentiment.

Sheet Offset Analysis
A1: Offset analysis: do domestic institutions absorb foreign selling?
A2: Complete months only (Jan 2017 to Sep 2026). A month is 'fully offset' when DII net buying is at least as large as FPI net selling. Flow series are preliminary; see Method & Sources.
A4: 1. Nifty returns by flow regime
A5: Regime | B5: Months | C5: Mean Nifty return | D5: Months with positive return | E5: Avg FPI flow (₹ cr) | F5: Avg DII flow (₹ cr)
A6: FPI net sellers (all) | B6: =COUNTIF('Monthly Data'!$G$5:$G$121,"Yes") -> 53 | C6: =AVERAGEIFS('Monthly Data'!$K$5:$K$121,'Monthly Data'!$G$5:$G$121,"Yes") -> -0.010780589 | D6: =COUNTIFS('Monthly Data'!$G$5:$G$121,"Yes",'Monthly Data'!$K$5:$K$121,">0")/COUNTIFS('Monthly Data'!$G$5:$G$121,"Yes",'Monthly Data'!$K$5:$K$121,">-1") -> 0.30769231 | E6: =AVERAGEIFS('Monthly Data'!$D$5:$D$121,'Monthly Data'!$G$5:$G$121,"Yes") -> -24577.132 | F6: =AVERAGEIFS('Monthly Data'!$E$5:$E$121,'Monthly Data'!$G$5:$G$121,"Yes") -> 38698.892
A7: of which fully offset by DII | B7: =COUNTIF('Monthly Data'!$H$5:$H$121,"Yes") -> 42 | C7: =AVERAGEIFS('Monthly Data'!$K$5:$K$121,'Monthly Data'!$H$5:$H$121,"Yes") -> -0.013251138 | D7: =COUNTIFS('Monthly Data'!$H$5:$H$121,"Yes",'Monthly Data'!$K$5:$K$121,">0")/COUNTIFS('Monthly Data'!$H$5:$H$121,"Yes",'Monthly Data'!$K$5:$K$121,">-1") -> 0.26829268 | E7: =AVERAGEIFS('Monthly Data'!$D$5:$D$121,'Monthly Data'!$H$5:$H$121,"Yes") -> -23590.119 | F7: =AVERAGEIFS('Monthly Data'!$E$5:$E$121,'Monthly Data'!$H$5:$H$121,"Yes") -> 42892.031
A8: of which not fully offset | B8: =COUNTIF('Monthly Data'!$H$5:$H$121,"No") -> 11 | C8: =AVERAGEIFS('Monthly Data'!$K$5:$K$121,'Monthly Data'!$H$5:$H$121,"No") -> -0.0015721774 | D8: =COUNTIFS('Monthly Data'!$H$5:$H$121,"No",'Monthly Data'!$K$5:$K$121,">0")/COUNTIFS('Monthly Data'!$H$5:$H$121,"No",'Monthly Data'!$K$5:$K$121,">-1") -> 0.45454545 | E8: =AVERAGEIFS('Monthly Data'!$D$5:$D$121,'Monthly Data'!$H$5:$H$121,"No") -> -28345.727 | F8: =AVERAGEIFS('Monthly Data'!$E$5:$E$121,'Monthly Data'!$H$5:$H$121,"No") -> 22688.727
A9: FPI not selling | B9: =COUNTIF('Monthly Data'!$G$5:$G$121,"No") -> 64 | C9: =AVERAGEIFS('Monthly Data'!$K$5:$K$121,'Monthly Data'!$G$5:$G$121,"No") -> 0.026080691 | D9: =COUNTIFS('Monthly Data'!$G$5:$G$121,"No",'Monthly Data'!$K$5:$K$121,">0")/COUNTIFS('Monthly Data'!$G$5:$G$121,"No",'Monthly Data'!$K$5:$K$121,">-1") -> 0.765625 | E9: =AVERAGEIFS('Monthly Data'!$D$5:$D$121,'Monthly Data'!$G$5:$G$121,"No") -> 19397.953 | F9: =AVERAGEIFS('Monthly Data'!$E$5:$E$121,'Monthly Data'!$G$5:$G$121,"No") -> 10416.261
A10: Full-offset rate (fully offset ÷ FPI-selling months) | B10: =B7/B6 -> 0.79245283
A11: January 2017 counts as a selling month but has no return (December 2016 close not in the dataset), so averages in column C use 52 observations.
A13: 2. Offset rate by period
A14: Period | B14: FPI-selling months | C14: Fully offset | D14: Offset rate | E14: Total months | F14: Selling months as share of period
A15: 2017 to 2019 | B15: =COUNTIFS('Monthly Data'!$G$5:$G$121,"Yes",'Monthly Data'!$B$5:$B$121,">=2017",'Monthly Data'!$B$5:$B$121,"<=2019") -> 13 | C15: =COUNTIFS('Monthly Data'!$H$5:$H$121,"Yes",'Monthly Data'!$B$5:$B$121,">=2017",'Monthly Data'!$B$5:$B$121,"<=2019") -> 11 | D15: =C15/B15 -> 0.84615385 | E15: =COUNTIFS('Monthly Data'!$B$5:$B$121,">=2017",'Monthly Data'!$B$5:$B$121,"<=2019") -> 36 | F15: =B15/E15 -> 0.36111111
A16: 2020 to 2023 | B16: =COUNTIFS('Monthly Data'!$G$5:$G$121,"Yes",'Monthly Data'!$B$5:$B$121,">=2020",'Monthly Data'!$B$5:$B$121,"<=2023") -> 21 | C16: =COUNTIFS('Monthly Data'!$H$5:$H$121,"Yes",'Monthly Data'!$B$5:$B$121,">=2020",'Monthly Data'!$B$5:$B$121,"<=2023") -> 13 | D16: =C16/B16 -> 0.61904762 | E16: =COUNTIFS('Monthly Data'!$B$5:$B$121,">=2020",'Monthly Data'!$B$5:$B$121,"<=2023") -> 48 | F16: =B16/E16 -> 0.4375
A17: 2024 to Sep 2026 | B17: =COUNTIFS('Monthly Data'!$G$5:$G$121,"Yes",'Monthly Data'!$B$5:$B$121,">=2024",'Monthly Data'!$B$5:$B$121,"<=2026") -> 19 | C17: =COUNTIFS('Monthly Data'!$H$5:$H$121,"Yes",'Monthly Data'!$B$5:$B$121,">=2024",'Monthly Data'!$B$5:$B$121,"<=2026") -> 18 | D17: =C17/B17 -> 0.94736842 | E17: =COUNTIFS('Monthly Data'!$B$5:$B$121,">=2024",'Monthly Data'!$B$5:$B$121,"<=2026") -> 33 | F17: =B17/E17 -> 0.57575758
A20: 3. Stress test: the ten largest monthly FPI outflows
A21: Rank | B21: Month | C21: FPI flow (₹ cr) | D21: DII flow (₹ cr) | E21: Offset ratio | F21: Fully offset? | G21: Nifty return | H21: SIP (₹ cr)
A22: 1 | B22: =INDEX('Monthly Data'!$A$5:$A$121,MATCH(C22,'Monthly Data'!$D$5:$D$121,0)) -> 46082 | C22: =SMALL('Monthly Data'!$D$5:$D$121,A22) -> -117775 | D22: =INDEX('Monthly Data'!$E$5:$E$121,MATCH(C22,'Monthly Data'!$D$5:$D$121,0)) -> 142960.4 | E22: =D22/-C22 -> 1.2138433 | F22: =IF(D22>=-C22,"Yes","No") -> Yes | G22: =INDEX('Monthly Data'!$K$5:$K$121,MATCH(C22,'Monthly Data'!$D$5:$D$121,0)) -> -0.11308192 | H22: =INDEX('Monthly Data'!$L$5:$L$121,MATCH(C22,'Monthly Data'!$D$5:$D$121,0)) -> 32087
A23: 2 | B23: =INDEX('Monthly Data'!$A$5:$A$121,MATCH(C23,'Monthly Data'!$D$5:$D$121,0)) -> 45566 | C23: =SMALL('Monthly Data'!$D$5:$D$121,A23) -> -94017 | D23: =INDEX('Monthly Data'!$E$5:$E$121,MATCH(C23,'Monthly Data'!$D$5:$D$121,0)) -> 107254.7 | E23: =D23/-C23 -> 1.1408011 | F23: =IF(D23>=-C23,"Yes","No") -> Yes | G23: =INDEX('Monthly Data'!$K$5:$K$121,MATCH(C23,'Monthly Data'!$D$5:$D$121,0)) -> -0.062202523 | H23: =INDEX('Monthly Data'!$L$5:$L$121,MATCH(C23,'Monthly Data'!$D$5:$D$121,0)) -> 25323
A24: 3 | B24: =INDEX('Monthly Data'!$A$5:$A$121,MATCH(C24,'Monthly Data'!$D$5:$D$121,0)) -> 45658 | C24: =SMALL('Monthly Data'!$D$5:$D$121,A24) -> -78027 | D24: =INDEX('Monthly Data'!$E$5:$E$121,MATCH(C24,'Monthly Data'!$D$5:$D$121,0)) -> 86591.8 | E24: =D24/-C24 -> 1.1097671 | F24: =IF(D24>=-C24,"Yes","No") -> Yes | G24: =INDEX('Monthly Data'!$K$5:$K$121,MATCH(C24,'Monthly Data'!$D$5:$D$121,0)) -> -0.0057687102 | H24: =INDEX('Monthly Data'!$L$5:$L$121,MATCH(C24,'Monthly Data'!$D$5:$D$121,0)) -> 26400
A25: 4 | B25: =INDEX('Monthly Data'!$A$5:$A$121,MATCH(C25,'Monthly Data'!$D$5:$D$121,0)) -> 43891 | C25: =SMALL('Monthly Data'!$D$5:$D$121,A25) -> -61973 | D25: =INDEX('Monthly Data'!$E$5:$E$121,MATCH(C25,'Monthly Data'!$D$5:$D$121,0)) -> 55595.2 | E25: =D25/-C25 -> 0.89708744 | F25: =IF(D25>=-C25,"Yes","No") -> No | G25: =INDEX('Monthly Data'!$K$5:$K$121,MATCH(C25,'Monthly Data'!$D$5:$D$121,0)) -> -0.23246368 | H25: =INDEX('Monthly Data'!$L$5:$L$121,MATCH(C25,'Monthly Data'!$D$5:$D$121,0)) -> 8641
A26: 5 | B26: =INDEX('Monthly Data'!$A$5:$A$121,MATCH(C26,'Monthly Data'!$D$5:$D$121,0)) -> 46113 | C26: =SMALL('Monthly Data'!$D$5:$D$121,A26) -> -60847 | D26: =INDEX('Monthly Data'!$E$5:$E$121,MATCH(C26,'Monthly Data'!$D$5:$D$121,0)) -> 51063.9 | E26: =D26/-C26 -> 0.83921804 | F26: =IF(D26>=-C26,"Yes","No") -> No | G26: =INDEX('Monthly Data'!$K$5:$K$121,MATCH(C26,'Monthly Data'!$D$5:$D$121,0)) -> 0.07461019 | H26: =INDEX('Monthly Data'!$L$5:$L$121,MATCH(C26,'Monthly Data'!$D$5:$D$121,0)) -> 31115
A27: 6 | B27: =INDEX('Monthly Data'!$A$5:$A$121,MATCH(C27,'Monthly Data'!$D$5:$D$121,0)) -> 44713 | C27: =SMALL('Monthly Data'!$D$5:$D$121,A27) -> -50203 | D27: =INDEX('Monthly Data'!$E$5:$E$121,MATCH(C27,'Monthly Data'!$D$5:$D$121,0)) -> 46599.2 | E27: =D27/-C27 -> 0.92821545 | F27: =IF(D27>=-C27,"Yes","No") -> No | G27: =INDEX('Monthly Data'!$K$5:$K$121,MATCH(C27,'Monthly Data'!$D$5:$D$121,0)) -> -0.048496944 | H27: =INDEX('Monthly Data'!$L$5:$L$121,MATCH(C27,'Monthly Data'!$D$5:$D$121,0)) -> 12276
A28: 7 | B28: =INDEX('Monthly Data'!$A$5:$A$121,MATCH(C28,'Monthly Data'!$D$5:$D$121,0)) -> 46174 | C28: =SMALL('Monthly Data'!$D$5:$D$121,A28) -> -49340 | D28: =INDEX('Monthly Data'!$E$5:$E$121,MATCH(C28,'Monthly Data'!$D$5:$D$121,0)) -> 85800.1 | E28: =D28/-C28 -> 1.7389562 | F28: =IF(D28>=-C28,"Yes","No") -> Yes | G28: =INDEX('Monthly Data'!$K$5:$K$121,MATCH(C28,'Monthly Data'!$D$5:$D$121,0)) -> 0.013504475 | H28: =INDEX('Monthly Data'!$L$5:$L$121,MATCH(C28,'Monthly Data'!$D$5:$D$121,0)) -> 31781
A29: 8 | B29: =INDEX('Monthly Data'!$A$5:$A$121,MATCH(C29,'Monthly Data'!$D$5:$D$121,0)) -> 44621 | C29: =SMALL('Monthly Data'!$D$5:$D$121,A29) -> -41123 | D29: =INDEX('Monthly Data'!$E$5:$E$121,MATCH(C29,'Monthly Data'!$D$5:$D$121,0)) -> 39677 | E29: =D29/-C29 -> 0.9648372 | F29: =IF(D29>=-C29,"Yes","No") -> No | G29: =INDEX('Monthly Data'!$K$5:$K$121,MATCH(C29,'Monthly Data'!$D$5:$D$121,0)) -> 0.039946052 | H29: =INDEX('Monthly Data'!$L$5:$L$121,MATCH(C29,'Monthly Data'!$D$5:$D$121,0)) -> 12328
A30: 9 | B30: =INDEX('Monthly Data'!$A$5:$A$121,MATCH(C30,'Monthly Data'!$D$5:$D$121,0)) -> 44682 | C30: =SMALL('Monthly Data'!$D$5:$D$121,A30) -> -39993 | D30: =INDEX('Monthly Data'!$E$5:$E$121,MATCH(C30,'Monthly Data'!$D$5:$D$121,0)) -> 50835.5 | E30: =D30/-C30 -> 1.2711099 | F30: =IF(D30>=-C30,"Yes","No") -> Yes | G30: =INDEX('Monthly Data'!$K$5:$K$121,MATCH(C30,'Monthly Data'!$D$5:$D$121,0)) -> -0.030287881 | H30: =INDEX('Monthly Data'!$L$5:$L$121,MATCH(C30,'Monthly Data'!$D$5:$D$121,0)) -> 12286
A31: 10 | B31: =INDEX('Monthly Data'!$A$5:$A$121,MATCH(C31,'Monthly Data'!$D$5:$D$121,0)) -> 46023 | C31: =SMALL('Monthly Data'!$D$5:$D$121,A31) -> -35962 | D31: =INDEX('Monthly Data'!$E$5:$E$121,MATCH(C31,'Monthly Data'!$D$5:$D$121,0)) -> 69220.7 | E31: =D31/-C31 -> 1.924829 | F31: =IF(D31>=-C31,"Yes","No") -> Yes | G31: =INDEX('Monthly Data'!$K$5:$K$121,MATCH(C31,'Monthly Data'!$D$5:$D$121,0)) -> -0.030959142 | H31: =INDEX('Monthly Data'!$L$5:$L$121,MATCH(C31,'Monthly Data'!$D$5:$D$121,0)) -> 31002
A34: Group | B34: Selling months | C34: Fully offset | D34: Offset rate | E34: Avg FPI (₹ cr) | F34: Avg DII (₹ cr) | G34: Mean Nifty return
A35: 10 largest FPI-selling months | B35: 10 | C35: =COUNTIF(F22:F31,"Yes") -> 6 | D35: =C35/B35 -> 0.6 | E35: =AVERAGE(C22:C31) -> -62926 | F35: =AVERAGE(D22:D31) -> 73559.85 | G35: =AVERAGE(G22:G31) -> -0.039520008
A36: All other FPI-selling months | B36: =B6-B35 -> 43 | C36: =B7-C35 -> 36 | D36: =C36/B36 -> 0.8372093 | E36: =(SUMIFS('Monthly Data'!$D$5:$D$121,'Monthly Data'!$G$5:$G$121,"Yes")-SUM(C22:C31))/B36 -> -15658.791 | F36: =(SUMIFS('Monthly Data'!$E$5:$E$121,'Monthly Data'!$G$5:$G$121,"Yes")-SUM(D22:D31))/B36 -> 30591.693 | G36: =(SUMIFS('Monthly Data'!$K$5:$K$121,'Monthly Data'!$G$5:$G$121,"Yes")-SUM(G22:G31))/(COUNTIFS('Monthly Data'!$G$5:$G$121,"Yes",'Monthly Data'!$K$5:$K$121,">-1")-10) -> -0.0039378696
A38: The ten-month group is small, so these averages are indicative only. Months are ranked by FPI flow; ties are not present in the data.

Sheet Correlations
A1: Correlation tests
A2: Pearson r is calculated live from Monthly Data. Spearman and the robustness checks were run in Python on the same data and are stored as values. All figures describe association, not cause.
A4: 1. Institutional flows and Nifty return (same month)
A5: Flow series | B5: Months (n) | C5: Pearson r | D5: Spearman ρ
A6: FPI net flow | B6: =SUMPRODUCT(--ISNUMBER('Monthly Data'!$D$5:$D$121),--ISNUMBER('Monthly Data'!$K$5:$K$121)) -> 116 | C6: =CORREL('Monthly Data'!$D$5:$D$121,'Monthly Data'!$K$5:$K$121) -> 0.53073101 | D6: 0.5011
A7: DII net flow | B7: =SUMPRODUCT(--ISNUMBER('Monthly Data'!$E$5:$E$121),--ISNUMBER('Monthly Data'!$K$5:$K$121)) -> 116 | C7: =CORREL('Monthly Data'!$E$5:$E$121,'Monthly Data'!$K$5:$K$121) -> -0.46724052 | D7: -0.4486
A8: FPI + DII combined | B8: =SUMPRODUCT(--ISNUMBER('Monthly Data'!$F$5:$F$121),--ISNUMBER('Monthly Data'!$K$5:$K$121)) -> 116 | C8: =CORREL('Monthly Data'!$F$5:$F$121,'Monthly Data'!$K$5:$K$121) -> 0.073524191 | D8: 0.064
A10: 2. Macro indicators
A11: Indicator | B11: Compared with | C11: Months (n) | D11: Pearson r | E11: Spearman ρ
A12: USD/INR monthly change | B12: Nifty return | C12: =SUMPRODUCT(--ISNUMBER('Monthly Data'!$O$5:$O$121),--ISNUMBER('Monthly Data'!$K$5:$K$121)) -> 107 | D12: =CORREL('Monthly Data'!$O$5:$O$121,'Monthly Data'!$K$5:$K$121) -> -0.51639924 | E12: -0.487
A13: USD/INR monthly change | B13: FPI net flow | C13: =SUMPRODUCT(--ISNUMBER('Monthly Data'!$O$5:$O$121),--ISNUMBER('Monthly Data'!$D$5:$D$121)) -> 107 | D13: =CORREL('Monthly Data'!$O$5:$O$121,'Monthly Data'!$D$5:$D$121) -> -0.35836188 | E13: -0.346
A14: USD/INR monthly change | B14: DII net flow | C14: =SUMPRODUCT(--ISNUMBER('Monthly Data'!$O$5:$O$121),--ISNUMBER('Monthly Data'!$E$5:$E$121)) -> 107 | D14: =CORREL('Monthly Data'!$O$5:$O$121,'Monthly Data'!$E$5:$E$121) -> 0.27830178 | E14: 0.269
A15: Repo rate | B15: Nifty return | C15: =SUMPRODUCT(--ISNUMBER('Monthly Data'!$Q$5:$Q$121),--ISNUMBER('Monthly Data'!$K$5:$K$121)) -> 108 | D15: =CORREL('Monthly Data'!$Q$5:$Q$121,'Monthly Data'!$K$5:$K$121) -> -0.061899374 | E15: -0.04
A16: Repo rate | B16: FPI net flow | C16: =SUMPRODUCT(--ISNUMBER('Monthly Data'!$Q$5:$Q$121),--ISNUMBER('Monthly Data'!$D$5:$D$121)) -> 108 | D16: =CORREL('Monthly Data'!$Q$5:$Q$121,'Monthly Data'!$D$5:$D$121) -> 0.042127075 | E16: 0.062
A17: Repo rate | B17: DII net flow | C17: =SUMPRODUCT(--ISNUMBER('Monthly Data'!$Q$5:$Q$121),--ISNUMBER('Monthly Data'!$E$5:$E$121)) -> 108 | D17: =CORREL('Monthly Data'!$Q$5:$Q$121,'Monthly Data'!$E$5:$E$121) -> 0.17210346 | E17: 0.168
A18: CPI inflation (YoY) | B18: Nifty return | C18: =SUMPRODUCT(--ISNUMBER('Monthly Data'!$P$5:$P$121),--ISNUMBER('Monthly Data'!$K$5:$K$121)) -> 116 | D18: =CORREL('Monthly Data'!$P$5:$P$121,'Monthly Data'!$K$5:$K$121) -> 0.025343519 | E18: 0.013
A19: CPI inflation (YoY) | B19: FPI net flow | C19: =SUMPRODUCT(--ISNUMBER('Monthly Data'!$P$5:$P$121),--ISNUMBER('Monthly Data'!$D$5:$D$121)) -> 117 | D19: =CORREL('Monthly Data'!$P$5:$P$121,'Monthly Data'!$D$5:$D$121) -> 0.074409529 | E19: 0.057
A20: CPI inflation (YoY) | B20: DII net flow | C20: =SUMPRODUCT(--ISNUMBER('Monthly Data'!$P$5:$P$121),--ISNUMBER('Monthly Data'!$E$5:$E$121)) -> 117 | D20: =CORREL('Monthly Data'!$P$5:$P$121,'Monthly Data'!$E$5:$E$121) -> -0.26450285 | E20: -0.183
A22: 3. Robustness of the USD/INR and Nifty relationship (stored values)
A23: Test | B23: Months (n) | C23: Pearson r | D23: Spearman ρ
A24: All complete months | B24: 107 | C24: -0.516 | D24: -0.487
A25: Excluding outer 2.5% tails of both variables | B25: 97 | C25: -0.37 | D25: -0.4
A26: 2017 to 2019 | B26: 26 | C26: -0.388 | D26: -0.318
A27: 2020 to 2023 | B27: 48 | C27: -0.657 | D27: -0.588
A28: 2024 to Sep 2026 | B28: 33 | C28: -0.611 | D28: -0.431
A30: 4. SIP and offsetting (stored values, FPI-selling months only, n = 53)
A31: SIP level vs fully-offset indicator | C31: 0.255
A32: SIP level vs offset ratio | C32: -0.041
A34: Reading the table: a negative r between USD/INR change and Nifty return means months of larger rupee depreciation tended to be months of weaker equity returns.

Sheet Annual Summary
A1: Annual summary
A2: Calculated from Monthly Data. 2026 covers January to September (nine complete months).
A4: Year | B4: Months | C4: FPI net flow (₹ cr) | D4: DII net flow (₹ cr) | E4: FPI-selling months | F4: Fully offset | G4: Avg monthly Nifty return | H4: SIP total (₹ cr) | I4: Avg monthly SIP (₹ cr)
A5: 2017 | B5: =COUNTIF('Monthly Data'!$B$5:$B$121,A5) -> 12 | C5: =SUMIFS('Monthly Data'!$D$5:$D$121,'Monthly Data'!$B$5:$B$121,A5) -> 51252 | D5: =SUMIFS('Monthly Data'!$E$5:$E$121,'Monthly Data'!$B$5:$B$121,A5) -> 90738.3 | E5: =COUNTIFS('Monthly Data'!$B$5:$B$121,A5,'Monthly Data'!$G$5:$G$121,"Yes") -> 4 | F5: =COUNTIFS('Monthly Data'!$B$5:$B$121,A5,'Monthly Data'!$H$5:$H$121,"Yes") -> 4 | G5: =AVERAGEIFS('Monthly Data'!$K$5:$K$121,'Monthly Data'!$B$5:$B$121,A5) -> 0.019347724 | H5: =SUMIFS('Monthly Data'!$L$5:$L$121,'Monthly Data'!$B$5:$B$121,A5) -> 59482 | I5: =H5/B5 -> 4956.8333
A6: 2018 | B6: =COUNTIF('Monthly Data'!$B$5:$B$121,A6) -> 12 | C6: =SUMIFS('Monthly Data'!$D$5:$D$121,'Monthly Data'!$B$5:$B$121,A6) -> -33014 | D6: =SUMIFS('Monthly Data'!$E$5:$E$121,'Monthly Data'!$B$5:$B$121,A6) -> 109661.8 | E6: =COUNTIFS('Monthly Data'!$B$5:$B$121,A6,'Monthly Data'!$G$5:$G$121,"Yes") -> 6 | F6: =COUNTIFS('Monthly Data'!$B$5:$B$121,A6,'Monthly Data'!$H$5:$H$121,"Yes") -> 5 | G6: =AVERAGEIFS('Monthly Data'!$K$5:$K$121,'Monthly Data'!$B$5:$B$121,A6) -> 0.0035394434 | H6: =SUMIFS('Monthly Data'!$L$5:$L$121,'Monthly Data'!$B$5:$B$121,A6) -> 88667 | I6: =H6/B6 -> 7388.9167
A7: 2019 | B7: =COUNTIF('Monthly Data'!$B$5:$B$121,A7) -> 12 | C7: =SUMIFS('Monthly Data'!$D$5:$D$121,'Monthly Data'!$B$5:$B$121,A7) -> 101122 | D7: =SUMIFS('Monthly Data'!$E$5:$E$121,'Monthly Data'!$B$5:$B$121,A7) -> 42257.2 | E7: =COUNTIFS('Monthly Data'!$B$5:$B$121,A7,'Monthly Data'!$G$5:$G$121,"Yes") -> 3 | F7: =COUNTIFS('Monthly Data'!$B$5:$B$121,A7,'Monthly Data'!$H$5:$H$121,"Yes") -> 2 | G7: =AVERAGEIFS('Monthly Data'!$K$5:$K$121,'Monthly Data'!$B$5:$B$121,A7) -> 0.0099901648 | H7: =SUMIFS('Monthly Data'!$L$5:$L$121,'Monthly Data'!$B$5:$B$121,A7) -> 98612 | I7: =H7/B7 -> 8217.6667
A8: 2020 | B8: =COUNTIF('Monthly Data'!$B$5:$B$121,A8) -> 12 | C8: =SUMIFS('Monthly Data'!$D$5:$D$121,'Monthly Data'!$B$5:$B$121,A8) -> 170262 | D8: =SUMIFS('Monthly Data'!$E$5:$E$121,'Monthly Data'!$B$5:$B$121,A8) -> -35663.2 | E8: =COUNTIFS('Monthly Data'!$B$5:$B$121,A8,'Monthly Data'!$G$5:$G$121,"Yes") -> 3 | F8: =COUNTIFS('Monthly Data'!$B$5:$B$121,A8,'Monthly Data'!$H$5:$H$121,"Yes") -> 0 | G8: =AVERAGEIFS('Monthly Data'!$K$5:$K$121,'Monthly Data'!$B$5:$B$121,A8) -> 0.016573749 | H8: =SUMIFS('Monthly Data'!$L$5:$L$121,'Monthly Data'!$B$5:$B$121,A8) -> 97033 | I8: =H8/B8 -> 8086.0833
A9: 2021 | B9: =COUNTIF('Monthly Data'!$B$5:$B$121,A9) -> 12 | C9: =SUMIFS('Monthly Data'!$D$5:$D$121,'Monthly Data'!$B$5:$B$121,A9) -> 25752 | D9: =SUMIFS('Monthly Data'!$E$5:$E$121,'Monthly Data'!$B$5:$B$121,A9) -> 95074.8 | E9: =COUNTIFS('Monthly Data'!$B$5:$B$121,A9,'Monthly Data'!$G$5:$G$121,"Yes") -> 6 | F9: =COUNTIFS('Monthly Data'!$B$5:$B$121,A9,'Monthly Data'!$H$5:$H$121,"Yes") -> 4 | G9: =AVERAGEIFS('Monthly Data'!$K$5:$K$121,'Monthly Data'!$B$5:$B$121,A9) -> 0.018797509 | H9: =SUMIFS('Monthly Data'!$L$5:$L$121,'Monthly Data'!$B$5:$B$121,A9) -> 114016 | I9: =H9/B9 -> 9501.3333
A10: 2022 | B10: =COUNTIF('Monthly Data'!$B$5:$B$121,A10) -> 12 | C10: =SUMIFS('Monthly Data'!$D$5:$D$121,'Monthly Data'!$B$5:$B$121,A10) -> -121439 | D10: =SUMIFS('Monthly Data'!$E$5:$E$121,'Monthly Data'!$B$5:$B$121,A10) -> 276698.7 | E10: =COUNTIFS('Monthly Data'!$B$5:$B$121,A10,'Monthly Data'!$G$5:$G$121,"Yes") -> 8 | F10: =COUNTIFS('Monthly Data'!$B$5:$B$121,A10,'Monthly Data'!$H$5:$H$121,"Yes") -> 5 | G10: =AVERAGEIFS('Monthly Data'!$K$5:$K$121,'Monthly Data'!$B$5:$B$121,A10) -> 0.0044445514 | H10: =SUMIFS('Monthly Data'!$L$5:$L$121,'Monthly Data'!$B$5:$B$121,A10) -> 149437 | I10: =H10/B10 -> 12453.083
A11: 2023 | B11: =COUNTIF('Monthly Data'!$B$5:$B$121,A11) -> 12 | C11: =SUMIFS('Monthly Data'!$D$5:$D$121,'Monthly Data'!$B$5:$B$121,A11) -> 171107 | D11: =SUMIFS('Monthly Data'!$E$5:$E$121,'Monthly Data'!$B$5:$B$121,A11) -> 184650.1 | E11: =COUNTIFS('Monthly Data'!$B$5:$B$121,A11,'Monthly Data'!$G$5:$G$121,"Yes") -> 4 | F11: =COUNTIFS('Monthly Data'!$B$5:$B$121,A11,'Monthly Data'!$H$5:$H$121,"Yes") -> 4 | G11: =AVERAGEIFS('Monthly Data'!$K$5:$K$121,'Monthly Data'!$B$5:$B$121,A11) -> 0.015886719 | H11: =SUMIFS('Monthly Data'!$L$5:$L$121,'Monthly Data'!$B$5:$B$121,A11) -> 183741 | I11: =H11/B11 -> 15311.75
A12: 2024 | B12: =COUNTIF('Monthly Data'!$B$5:$B$121,A12) -> 12 | C12: =SUMIFS('Monthly Data'!$D$5:$D$121,'Monthly Data'!$B$5:$B$121,A12) -> 427 | D12: =SUMIFS('Monthly Data'!$E$5:$E$121,'Monthly Data'!$B$5:$B$121,A12) -> 526545.1 | E12: =COUNTIFS('Monthly Data'!$B$5:$B$121,A12,'Monthly Data'!$G$5:$G$121,"Yes") -> 5 | F12: =COUNTIFS('Monthly Data'!$B$5:$B$121,A12,'Monthly Data'!$H$5:$H$121,"Yes") -> 5 | G12: =AVERAGEIFS('Monthly Data'!$K$5:$K$121,'Monthly Data'!$B$5:$B$121,A12) -> 0.0075018727 | H12: =SUMIFS('Monthly Data'!$L$5:$L$121,'Monthly Data'!$B$5:$B$121,A12) -> 268323 | I12: =H12/B12 -> 22360.25
A13: 2025 | B13: =COUNTIF('Monthly Data'!$B$5:$B$121,A13) -> 12 | C13: =SUMIFS('Monthly Data'!$D$5:$D$121,'Monthly Data'!$B$5:$B$121,A13) -> -166286 | D13: =SUMIFS('Monthly Data'!$E$5:$E$121,'Monthly Data'!$B$5:$B$121,A13) -> 788184.4 | E13: =COUNTIFS('Monthly Data'!$B$5:$B$121,A13,'Monthly Data'!$G$5:$G$121,"Yes") -> 8 | F13: =COUNTIFS('Monthly Data'!$B$5:$B$121,A13,'Monthly Data'!$H$5:$H$121,"Yes") -> 8 | G13: =AVERAGEIFS('Monthly Data'!$K$5:$K$121,'Monthly Data'!$B$5:$B$121,A13) -> 0.0088819056 | H13: =SUMIFS('Monthly Data'!$L$5:$L$121,'Monthly Data'!$B$5:$B$121,A13) -> 334980 | I13: =H13/B13 -> 27915
A14: 2026 | B14: =COUNTIF('Monthly Data'!$B$5:$B$121,A14) -> 9 | C14: =SUMIFS('Monthly Data'!$D$5:$D$121,'Monthly Data'!$B$5:$B$121,A14) -> -260302 | D14: =SUMIFS('Monthly Data'!$E$5:$E$121,'Monthly Data'!$B$5:$B$121,A14) -> 639534.8 | E14: =COUNTIFS('Monthly Data'!$B$5:$B$121,A14,'Monthly Data'!$G$5:$G$121,"Yes") -> 6 | F14: =COUNTIFS('Monthly Data'!$B$5:$B$121,A14,'Monthly Data'!$H$5:$H$121,"Yes") -> 5 | G14: =AVERAGEIFS('Monthly Data'!$K$5:$K$121,'Monthly Data'!$B$5:$B$121,A14) -> -0.014626924 | H14: =SUMIFS('Monthly Data'!$L$5:$L$121,'Monthly Data'!$B$5:$B$121,A14) -> 283532 | I14: =H14/B14 -> 31503.556
A15: Total | B15: =SUM(B5:B14) -> 117 | C15: =SUM(C5:C14) -> -61119 | D15: =SUM(D5:D14) -> 2717682 | E15: =SUM(E5:E14) -> 53 | F15: =SUM(F5:F14) -> 42 | H15: =SUM(H5:H14) -> 1677823

Sheet Monthly Data
A1: Monthly dataset, January 2017 to October 2026
A2: Blue = source data entered as values; black = calculated. Analysis uses complete months only (rows 5 to 121). October 2026 (row 122) is partial, to 23 Oct, and is shown for reference.
A4: Month | B4: Year | C4: Status | D4: FPI net flow (₹ cr) | E4: DII net flow (₹ cr) | F4: FPI + DII (₹ cr) | G4: FPI selling? | H4: DII fully offsets? | I4: Offset ratio (DII ÷ FPI selling) | J4: Nifty 50 close | K4: Nifty monthly return | L4: SIP contribution (₹ cr) | M4: Equity MF AUM (₹ cr, quarter-end) | N4: USD/INR (month-end) | O4: USD/INR monthly change | P4: CPI inflation (YoY, %) | Q4: Repo rate (%)
A5: 42736 | B5: =YEAR(A5) -> 2017 | C5: Complete | D5: -1177 | E5: 4503.9 | F5: =D5+E5 -> 3326.9 | G5: =IF(D5<0,"Yes","No") -> Yes | H5: =IF(D5<0,IF(E5>=-D5,"Yes","No"),"n/a") -> Yes | I5: =IF(D5<0,E5/-D5,"") -> 3.826593 | J5: 8561.3 | L5: 4095 | P5: 3.2
A6: 42767 | B6: =YEAR(A6) -> 2017 | C6: Complete | D6: 9902 | E6: 935.3 | F6: =D6+E6 -> 10837.3 | G6: =IF(D6<0,"Yes","No") -> No | H6: =IF(D6<0,IF(E6>=-D6,"Yes","No"),"n/a") -> n/a | I6: =IF(D6<0,E6/-D6,"") | J6: 8879.6 | K6: =J6/J5-1 -> 0.037178933 | L6: 4050 | P6: 3.7
A7: 42795 | B7: =YEAR(A7) -> 2017 | C7: Complete | D7: 30906 | E7: -4395.6 | F7: =D7+E7 -> 26510.4 | G7: =IF(D7<0,"Yes","No") -> No | H7: =IF(D7<0,IF(E7>=-D7,"Yes","No"),"n/a") -> n/a | I7: =IF(D7<0,E7/-D7,"") | J7: 9173.75 | K7: =J7/J6-1 -> 0.033126492 | L7: 4335 | M7: 543541.22 | P7: 3.9
A8: 42826 | B8: =YEAR(A8) -> 2017 | C8: Complete | D8: 2394 | E8: 9247.4 | F8: =D8+E8 -> 11641.4 | G8: =IF(D8<0,"Yes","No") -> No | H8: =IF(D8<0,IF(E8>=-D8,"Yes","No"),"n/a") -> n/a | I8: =IF(D8<0,E8/-D8,"") | J8: 9304.05 | K8: =J8/J7-1 -> 0.01420357 | L8: 4269 | P8: 3
A9: 42856 | B9: =YEAR(A9) -> 2017 | C9: Complete | D9: 7711 | E9: 4277.1 | F9: =D9+E9 -> 11988.1 | G9: =IF(D9<0,"Yes","No") -> No | H9: =IF(D9<0,IF(E9>=-D9,"Yes","No"),"n/a") -> n/a | I9: =IF(D9<0,E9/-D9,"") | J9: 9621.25 | K9: =J9/J8-1 -> 0.03409268 | L9: 4584 | P9: 2.2
A10: 42887 | B10: =YEAR(A10) -> 2017 | C10: Complete | D10: 3617 | E10: 6676.1 | F10: =D10+E10 -> 10293.1 | G10: =IF(D10<0,"Yes","No") -> No | H10: =IF(D10<0,IF(E10>=-D10,"Yes","No"),"n/a") -> n/a | I10: =IF(D10<0,E10/-D10,"") | J10: 9520.9 | K10: =J10/J9-1 -> -0.010430038 | L10: 4744 | M10: 591376.9 | P10: 1.5
A11: 42917 | B11: =YEAR(A11) -> 2017 | C11: Complete | D11: 5161 | E11: 4786.4 | F11: =D11+E11 -> 9947.4 | G11: =IF(D11<0,"Yes","No") -> No | H11: =IF(D11<0,IF(E11>=-D11,"Yes","No"),"n/a") -> n/a | I11: =IF(D11<0,E11/-D11,"") | J11: 10077.1 | K11: =J11/J10-1 -> 0.058418847 | L11: 4947 | P11: 2.4
A12: 42948 | B12: =YEAR(A12) -> 2017 | C12: Complete | D12: -12770 | E12: 16205.2 | F12: =D12+E12 -> 3435.2 | G12: =IF(D12<0,"Yes","No") -> Yes | H12: =IF(D12<0,IF(E12>=-D12,"Yes","No"),"n/a") -> Yes | I12: =IF(D12<0,E12/-D12,"") -> 1.2690055 | J12: 9917.9 | K12: =J12/J11-1 -> -0.015798196 | L12: 5206 | P12: 3.3
A13: 42979 | B13: =YEAR(A13) -> 2017 | C13: Complete | D13: -11392 | E13: 21025.5 | F13: =D13+E13 -> 9633.5 | G13: =IF(D13<0,"Yes","No") -> Yes | H13: =IF(D13<0,IF(E13>=-D13,"Yes","No"),"n/a") -> Yes | I13: =IF(D13<0,E13/-D13,"") -> 1.8456373 | J13: 9788.6 | K13: =J13/J12-1 -> -0.013037034 | L13: 5516 | M13: 659182.64 | P13: 3.3
A14: 43009 | B14: =YEAR(A14) -> 2017 | C14: Complete | D14: 3055 | E14: 10090.9 | F14: =D14+E14 -> 13145.9 | G14: =IF(D14<0,"Yes","No") -> No | H14: =IF(D14<0,IF(E14>=-D14,"Yes","No"),"n/a") -> n/a | I14: =IF(D14<0,E14/-D14,"") | J14: 10335.3 | K14: =J14/J13-1 -> 0.055850683 | L14: 5621 | N14: 64.7745 | P14: 3.6 | Q14: 6
A15: 43040 | B15: =YEAR(A15) -> 2017 | C15: Complete | D15: 19728 | E15: 9243.2 | F15: =D15+E15 -> 28971.2 | G15: =IF(D15<0,"Yes","No") -> No | H15: =IF(D15<0,IF(E15>=-D15,"Yes","No"),"n/a") -> n/a | I15: =IF(D15<0,E15/-D15,"") | J15: 10226.55 | K15: =J15/J14-1 -> -0.010522191 | L15: 5893 | N15: 64.4332 | O15: =N15/N14-1 -> -0.0052690488 | P15: 4.9 | Q15: 6
A16: 43070 | B16: =YEAR(A16) -> 2017 | C16: Complete | D16: -5883 | E16: 8142.9 | F16: =D16+E16 -> 2259.9 | G16: =IF(D16<0,"Yes","No") -> Yes | H16: =IF(D16<0,IF(E16>=-D16,"Yes","No"),"n/a") -> Yes | I16: =IF(D16<0,E16/-D16,"") -> 1.3841407 | J16: 10530.7 | K16: =J16/J15-1 -> 0.029741213 | L16: 6222 | M16: 771134.5 | N16: 63.9273 | O16: =N16/N15-1 -> -0.0078515424 | P16: 5.2 | Q16: 6
A17: 43101 | B17: =YEAR(A17) -> 2018 | C17: Complete | D17: 13781 | E17: 398.7 | F17: =D17+E17 -> 14179.7 | G17: =IF(D17<0,"Yes","No") -> No | H17: =IF(D17<0,IF(E17>=-D17,"Yes","No"),"n/a") -> n/a | I17: =IF(D17<0,E17/-D17,"") | J17: 11027.7 | K17: =J17/J16-1 -> 0.047195343 | L17: 6644 | N17: 63.6878 | O17: =N17/N16-1 -> -0.0037464432 | P17: 5.1 | Q17: 6
A18: 43132 | B18: =YEAR(A18) -> 2018 | C18: Complete | D18: -11423 | E18: 17813 | F18: =D18+E18 -> 6390 | G18: =IF(D18<0,"Yes","No") -> Yes | H18: =IF(D18<0,IF(E18>=-D18,"Yes","No"),"n/a") -> Yes | I18: =IF(D18<0,E18/-D18,"") -> 1.5593977 | J18: 10492.85 | K18: =J18/J17-1 -> -0.048500594 | L18: 6425 | N18: 65.1031 | O18: =N18/N17-1 -> 0.022222466 | P18: 4.4 | Q18: 6
A19: 43160 | B19: =YEAR(A19) -> 2018 | C19: Complete | D19: 11654 | E19: 6693.9 | F19: =D19+E19 -> 18347.9 | G19: =IF(D19<0,"Yes","No") -> No | H19: =IF(D19<0,IF(E19>=-D19,"Yes","No"),"n/a") -> n/a | I19: =IF(D19<0,E19/-D19,"") | J19: 10113.7 | K19: =J19/J18-1 -> -0.036134129 | L19: 7119 | M19: 749789.68 | N19: 65.0441 | O19: =N19/N18-1 -> -0.00090625485 | P19: 4.3 | Q19: 6
A20: 43191 | B20: =YEAR(A20) -> 2018 | C20: Complete | D20: -5552 | E20: 8663.9 | F20: =D20+E20 -> 3111.9 | G20: =IF(D20<0,"Yes","No") -> Yes | H20: =IF(D20<0,IF(E20>=-D20,"Yes","No"),"n/a") -> Yes | I20: =IF(D20<0,E20/-D20,"") -> 1.5605007 | J20: 10739.35 | K20: =J20/J19-1 -> 0.061861633 | L20: 6690 | N20: 66.7801 | O20: =N20/N19-1 -> 0.026689584 | P20: 4.6 | Q20: 6
A21: 43221 | B21: =YEAR(A21) -> 2018 | C21: Complete | D21: -10060 | E21: 15054.5 | F21: =D21+E21 -> 4994.5 | G21: =IF(D21<0,"Yes","No") -> Yes | H21: =IF(D21<0,IF(E21>=-D21,"Yes","No"),"n/a") -> Yes | I21: =IF(D21<0,E21/-D21,"") -> 1.4964712 | J21: 10736.15 | K21: =J21/J20-1 -> -0.00029796962 | L21: 7304 | N21: 67.4526 | O21: =N21/N20-1 -> 0.010070365 | P21: 4.9 | Q21: 6
A22: 43252 | B22: =YEAR(A22) -> 2018 | C22: Complete | D22: -4831 | E22: 14146.2 | F22: =D22+E22 -> 9315.2 | G22: =IF(D22<0,"Yes","No") -> Yes | H22: =IF(D22<0,IF(E22>=-D22,"Yes","No"),"n/a") -> Yes | I22: =IF(D22<0,E22/-D22,"") -> 2.9282136 | J22: 10714.3 | K22: =J22/J21-1 -> -0.0020351802 | L22: 7554 | M22: 786591.17 | N22: 68.5753 | O22: =N22/N21-1 -> 0.016644281 | P22: 4.9 | Q22: 6.25
A23: 43282 | B23: =YEAR(A23) -> 2018 | C23: Complete | D23: 2264 | E23: 3845.9 | F23: =D23+E23 -> 6109.9 | G23: =IF(D23<0,"Yes","No") -> No | H23: =IF(D23<0,IF(E23>=-D23,"Yes","No"),"n/a") -> n/a | I23: =IF(D23<0,E23/-D23,"") | J23: 11356.5 | K23: =J23/J22-1 -> 0.059938587 | L23: 7554 | N23: 68.6068 | O23: =N23/N22-1 -> 0.00045934907 | P23: 4.2 | Q23: 6.25
A24: 43313 | B24: =YEAR(A24) -> 2018 | C24: Complete | D24: 1775 | E24: 2822.7 | F24: =D24+E24 -> 4597.7 | G24: =IF(D24<0,"Yes","No") -> No | H24: =IF(D24<0,IF(E24>=-D24,"Yes","No"),"n/a") -> n/a | I24: =IF(D24<0,E24/-D24,"") | J24: 11680.5 | K24: =J24/J23-1 -> 0.028529917 | L24: 7658 | N24: 70.9255 | O24: =N24/N23-1 -> 0.033796941 | P24: 3.7 | Q24: 6.5
A25: 43344 | B25: =YEAR(A25) -> 2018 | C25: Complete | D25: -10825 | E25: 12504 | F25: =D25+E25 -> 1679 | G25: =IF(D25<0,"Yes","No") -> Yes | H25: =IF(D25<0,IF(E25>=-D25,"Yes","No"),"n/a") -> Yes | I25: =IF(D25<0,E25/-D25,"") -> 1.1551039 | J25: 10930.45 | K25: =J25/J24-1 -> -0.064213861 | L25: 7727 | M25: 802215.26 | N25: 72.5474 | O25: =N25/N24-1 -> 0.022867657 | P25: 3.7 | Q25: 6.5
A26: 43374 | B26: =YEAR(A26) -> 2018 | C26: Complete | D26: -28921 | E26: 26033.9 | F26: =D26+E26 -> -2887.1 | G26: =IF(D26<0,"Yes","No") -> Yes | H26: =IF(D26<0,IF(E26>=-D26,"Yes","No"),"n/a") -> No | I26: =IF(D26<0,E26/-D26,"") -> 0.90017288 | J26: 10386.6 | K26: =J26/J25-1 -> -0.0497555 | L26: 7985 | N26: 73.9936 | O26: =N26/N25-1 -> 0.019934553 | P26: 3.38 | Q26: 6.5
A27: 43405 | B27: =YEAR(A27) -> 2018 | C27: Complete | D27: 5981 | E27: 1309.5 | F27: =D27+E27 -> 7290.5 | G27: =IF(D27<0,"Yes","No") -> No | H27: =IF(D27<0,IF(E27>=-D27,"Yes","No"),"n/a") -> n/a | I27: =IF(D27<0,E27/-D27,"") | J27: 10876.75 | K27: =J27/J26-1 -> 0.047190611 | L27: 7985 | N27: 69.6574 | O27: =N27/N26-1 -> -0.058602366 | P27: 2.33 | Q27: 6.5
A28: 43435 | B28: =YEAR(A28) -> 2018 | C28: Complete | D28: 3143 | E28: 375.6 | F28: =D28+E28 -> 3518.6 | G28: =IF(D28<0,"Yes","No") -> No | H28: =IF(D28<0,IF(E28>=-D28,"Yes","No"),"n/a") -> n/a | I28: =IF(D28<0,E28/-D28,"") | J28: 10862.55 | K28: =J28/J27-1 -> -0.001305537 | L28: 8022 | M28: 844054.16 | N28: 69.7923 | O28: =N28/N27-1 -> 0.0019366212 | P28: 2.11 | Q28: 6.5
A29: 43466 | B29: =YEAR(A29) -> 2019 | C29: Complete | D29: -4262 | E29: 2146.9 | F29: =D29+E29 -> -2115.1 | G29: =IF(D29<0,"Yes","No") -> Yes | H29: =IF(D29<0,IF(E29>=-D29,"Yes","No"),"n/a") -> No | I29: =IF(D29<0,E29/-D29,"") -> 0.50373064 | J29: 10830.95 | K29: =J29/J28-1 -> -0.0029090775 | L29: 8064 | N29: 71.0333 | O29: =N29/N28-1 -> 0.017781331 | P29: 1.97 | Q29: 6.5
A30: 43497 | B30: =YEAR(A30) -> 2019 | C30: Complete | D30: 17220 | E30: -565.9 | F30: =D30+E30 -> 16654.1 | G30: =IF(D30<0,"Yes","No") -> No | H30: =IF(D30<0,IF(E30>=-D30,"Yes","No"),"n/a") -> n/a | I30: =IF(D30<0,E30/-D30,"") | J30: 10792.5 | K30: =J30/J29-1 -> -0.0035500118 | L30: 8095 | N30: 71.1953 | O30: =N30/N29-1 -> 0.0022806205 | P30: 2.57 | Q30: 6.25
A31: 43525 | B31: =YEAR(A31) -> 2019 | C31: Complete | D31: 33981 | E31: -13930.2 | F31: =D31+E31 -> 20050.8 | G31: =IF(D31<0,"Yes","No") -> No | H31: =IF(D31<0,IF(E31>=-D31,"Yes","No"),"n/a") -> n/a | I31: =IF(D31<0,E31/-D31,"") | J31: 11623.9 | K31: =J31/J30-1 -> 0.077034978 | L31: 8055 | M31: 892101.03 | N31: 69.1713 | O31: =N31/N30-1 -> -0.028428843 | P31: 2.86 | Q31: 6.25
A32: 43556 | B32: =YEAR(A32) -> 2019 | C32: Complete | D32: 21193 | E32: -4219.5 | F32: =D32+E32 -> 16973.5 | G32: =IF(D32<0,"Yes","No") -> No | H32: =IF(D32<0,IF(E32>=-D32,"Yes","No"),"n/a") -> n/a | I32: =IF(D32<0,E32/-D32,"") | J32: 11748.15 | K32: =J32/J31-1 -> 0.010689183 | L32: 8238 | N32: 69.8368 | O32: =N32/N31-1 -> 0.0096210423 | P32: 2.99 | Q32: 6
A33: 43586 | B33: =YEAR(A33) -> 2019 | C33: Complete | D33: 7920 | E33: 5316.3 | F33: =D33+E33 -> 13236.3 | G33: =IF(D33<0,"Yes","No") -> No | H33: =IF(D33<0,IF(E33>=-D33,"Yes","No"),"n/a") -> n/a | I33: =IF(D33<0,E33/-D33,"") | J33: 11922.8 | K33: =J33/J32-1 -> 0.01486617 | L33: 8183 | N33: 69.8058 | O33: =N33/N32-1 -> -0.00044389205 | P33: 3.05 | Q33: 6
A34: 43617 | B34: =YEAR(A34) -> 2019 | C34: Complete | D34: 2596 | E34: 3643.3 | F34: =D34+E34 -> 6239.3 | G34: =IF(D34<0,"Yes","No") -> No | H34: =IF(D34<0,IF(E34>=-D34,"Yes","No"),"n/a") -> n/a | I34: =IF(D34<0,E34/-D34,"") | J34: 11788.85 | K34: =J34/J33-1 -> -0.011234777 | L34: 8122 | M34: 760189.57 | N34: 68.918 | O34: =N34/N33-1 -> -0.012718141 | P34: 3.18 | Q34: 5.75
A35: 43647 | B35: =YEAR(A35) -> 2019 | C35: Complete | D35: -12419 | E35: 20394.5 | F35: =D35+E35 -> 7975.5 | G35: =IF(D35<0,"Yes","No") -> Yes | H35: =IF(D35<0,IF(E35>=-D35,"Yes","No"),"n/a") -> Yes | I35: =IF(D35<0,E35/-D35,"") -> 1.6422015 | J35: 11118 | K35: =J35/J34-1 -> -0.056905466 | L35: 8324 | N35: 68.8569 | O35: =N35/N34-1 -> -0.00088656084 | P35: 3.15 | Q35: 5.75
A36: 43678 | B36: =YEAR(A36) -> 2019 | C36: Complete | D36: -17592 | E36: 20933.6 | F36: =D36+E36 -> 3341.6 | G36: =IF(D36<0,"Yes","No") -> Yes | H36: =IF(D36<0,IF(E36>=-D36,"Yes","No"),"n/a") -> Yes | I36: =IF(D36<0,E36/-D36,"") -> 1.18995 | J36: 11023.25 | K36: =J36/J35-1 -> -0.0085222162 | L36: 8231 | N36: 71.7586 | O36: =N36/N35-1 -> 0.04214102 | P36: 3.28 | Q36: 5.4
A37: 43709 | B37: =YEAR(A37) -> 2019 | C37: Complete | D37: 7548 | E37: 12490.8 | F37: =D37+E37 -> 20038.8 | G37: =IF(D37<0,"Yes","No") -> No | H37: =IF(D37<0,IF(E37>=-D37,"Yes","No"),"n/a") -> n/a | I37: =IF(D37<0,E37/-D37,"") | J37: 11474.45 | K37: =J37/J36-1 -> 0.040931667 | L37: 8263 | M37: 759324.71 | N37: 70.685 | O37: =N37/N36-1 -> -0.014961273 | P37: 3.99 | Q37: 5.4
A38: 43739 | B38: =YEAR(A38) -> 2019 | C38: Complete | D38: 12368 | E38: 4758.5 | F38: =D38+E38 -> 17126.5 | G38: =IF(D38<0,"Yes","No") -> No | H38: =IF(D38<0,IF(E38>=-D38,"Yes","No"),"n/a") -> n/a | I38: =IF(D38<0,E38/-D38,"") | J38: 11877.45 | K38: =J38/J37-1 -> 0.035121509 | L38: 8246 | N38: 70.8095 | O38: =N38/N37-1 -> 0.0017613355 | P38: 4.62 | Q38: 5.15
A39: 43770 | B39: =YEAR(A39) -> 2019 | C39: Complete | D39: 25231 | E39: -7970.3 | F39: =D39+E39 -> 17260.7 | G39: =IF(D39<0,"Yes","No") -> No | H39: =IF(D39<0,IF(E39>=-D39,"Yes","No"),"n/a") -> n/a | I39: =IF(D39<0,E39/-D39,"") | J39: 12056.05 | K39: =J39/J38-1 -> 0.015036898 | L39: 8273 | N39: 71.7255 | O39: =N39/N38-1 -> 0.012936117 | P39: 5.54 | Q39: 5.15
A40: 43800 | B40: =YEAR(A40) -> 2019 | C40: Complete | D40: 7338 | E40: -740.8 | F40: =D40+E40 -> 6597.2 | G40: =IF(D40<0,"Yes","No") -> No | H40: =IF(D40<0,IF(E40>=-D40,"Yes","No"),"n/a") -> n/a | I40: =IF(D40<0,E40/-D40,"") | J40: 12168.45 | K40: =J40/J39-1 -> 0.0093231199 | L40: 8518 | M40: 805797.82 | N40: 71.274 | O40: =N40/N39-1 -> -0.0062948324 | P40: 7.35 | Q40: 5.15
A41: 43831 | B41: =YEAR(A41) -> 2020 | C41: Complete | D41: 12123 | E41: 1073.5 | F41: =D41+E41 -> 13196.5 | G41: =IF(D41<0,"Yes","No") -> No | H41: =IF(D41<0,IF(E41>=-D41,"Yes","No"),"n/a") -> n/a | I41: =IF(D41<0,E41/-D41,"") | J41: 11962.1 | K41: =J41/J40-1 -> -0.016957788 | L41: 8532 | N41: 71.5096 | O41: =N41/N40-1 -> 0.0033055532 | P41: 7.59 | Q41: 5.15
A42: 43862 | B42: =YEAR(A42) -> 2020 | C42: Complete | D42: 1820 | E42: 16933 | F42: =D42+E42 -> 18753 | G42: =IF(D42<0,"Yes","No") -> No | H42: =IF(D42<0,IF(E42>=-D42,"Yes","No"),"n/a") -> n/a | I42: =IF(D42<0,E42/-D42,"") | J42: 11201.75 | K42: =J42/J41-1 -> -0.063563254 | L42: 8513 | N42: 72.1895 | O42: =N42/N41-1 -> 0.0095078143 | P42: 6.58 | Q42: 5.15
A43: 43891 | B43: =YEAR(A43) -> 2020 | C43: Complete | D43: -61973 | E43: 55595.2 | F43: =D43+E43 -> -6377.8 | G43: =IF(D43<0,"Yes","No") -> Yes | H43: =IF(D43<0,IF(E43>=-D43,"Yes","No"),"n/a") -> No | I43: =IF(D43<0,E43/-D43,"") -> 0.89708744 | J43: 8597.75 | K43: =J43/J42-1 -> -0.23246368 | L43: 8641 | M43: 604661.2 | N43: 75.3859 | O43: =N43/N42-1 -> 0.044277907 | P43: 5.84 | Q43: 4.4
A44: 43922 | B44: =YEAR(A44) -> 2020 | C44: Complete | D44: -6884 | E44: -117 | F44: =D44+E44 -> -7001 | G44: =IF(D44<0,"Yes","No") -> Yes | H44: =IF(D44<0,IF(E44>=-D44,"Yes","No"),"n/a") -> No | I44: =IF(D44<0,E44/-D44,"") -> -0.016995933 | J44: 9859.9 | K44: =J44/J43-1 -> 0.14680003 | L44: 8376 | N44: 75.115 | O44: =N44/N43-1 -> -0.0035935102 | P44: 7.22 | Q44: 4.4
A45: 43952 | B45: =YEAR(A45) -> 2020 | C45: Complete | D45: 14569 | E45: 12293.2 | F45: =D45+E45 -> 26862.2 | G45: =IF(D45<0,"Yes","No") -> No | H45: =IF(D45<0,IF(E45>=-D45,"Yes","No"),"n/a") -> n/a | I45: =IF(D45<0,E45/-D45,"") | J45: 9580.3 | K45: =J45/J44-1 -> -0.028357286 | L45: 8123 | N45: 75.6369 | O45: =N45/N44-1 -> 0.006948013 | P45: 6.27 | Q45: 4
A46: 43983 | B46: =YEAR(A46) -> 2020 | C46: Complete | D46: 21832 | E46: 2434.4 | F46: =D46+E46 -> 24266.4 | G46: =IF(D46<0,"Yes","No") -> No | H46: =IF(D46<0,IF(E46>=-D46,"Yes","No"),"n/a") -> n/a | I46: =IF(D46<0,E46/-D46,"") | J46: 10302.1 | K46: =J46/J45-1 -> 0.075342108 | L46: 7917 | M46: 729833.88 | N46: 75.527 | O46: =N46/N45-1 -> -0.0014529945 | P46: 6.09 | Q46: 4
A47: 44013 | B47: =YEAR(A47) -> 2020 | C47: Complete | D47: 7563 | E47: -10007.9 | F47: =D47+E47 -> -2444.9 | G47: =IF(D47<0,"Yes","No") -> No | H47: =IF(D47<0,IF(E47>=-D47,"Yes","No"),"n/a") -> n/a | I47: =IF(D47<0,E47/-D47,"") | J47: 11073.45 | K47: =J47/J46-1 -> 0.074873084 | L47: 7831 | N47: 74.7722 | O47: =N47/N46-1 -> -0.0099937771 | P47: 6.73 | Q47: 4
A48: 44044 | B48: =YEAR(A48) -> 2020 | C48: Complete | D48: 47080 | E48: -11046.8 | F48: =D48+E48 -> 36033.2 | G48: =IF(D48<0,"Yes","No") -> No | H48: =IF(D48<0,IF(E48>=-D48,"Yes","No"),"n/a") -> n/a | I48: =IF(D48<0,E48/-D48,"") | J48: 11387.5 | K48: =J48/J47-1 -> 0.028360628 | L48: 7792 | N48: 73.5951 | O48: =N48/N47-1 -> -0.015742482 | P48: 6.69 | Q48: 4
A49: 44075 | B49: =YEAR(A49) -> 2020 | C49: Complete | D49: -7783 | E49: 110.3 | F49: =D49+E49 -> -7672.7 | G49: =IF(D49<0,"Yes","No") -> Yes | H49: =IF(D49<0,IF(E49>=-D49,"Yes","No"),"n/a") -> No | I49: =IF(D49<0,E49/-D49,"") -> 0.014171913 | J49: 11247.55 | K49: =J49/J48-1 -> -0.012289791 | L49: 7788 | M49: 793660.29 | N49: 73.7978 | O49: =N49/N48-1 -> 0.0027542595 | P49: 7.27 | Q49: 4
A50: 44105 | B50: =YEAR(A50) -> 2020 | C50: Complete | D50: 19541 | E50: -17318.4 | F50: =D50+E50 -> 2222.6 | G50: =IF(D50<0,"Yes","No") -> No | H50: =IF(D50<0,IF(E50>=-D50,"Yes","No"),"n/a") -> n/a | I50: =IF(D50<0,E50/-D50,"") | J50: 11642.4 | K50: =J50/J49-1 -> 0.035105423 | L50: 7800 | N50: 73.9732 | O50: =N50/N49-1 -> 0.0023767646 | P50: 7.61 | Q50: 4
A51: 44136 | B51: =YEAR(A51) -> 2020 | C51: Complete | D51: 60358 | E51: -48319.2 | F51: =D51+E51 -> 12038.8 | G51: =IF(D51<0,"Yes","No") -> No | H51: =IF(D51<0,IF(E51>=-D51,"Yes","No"),"n/a") -> n/a | I51: =IF(D51<0,E51/-D51,"") | J51: 12968.95 | K51: =J51/J50-1 -> 0.11394128 | L51: 7302 | N51: 73.7983 | O51: =N51/N50-1 -> -0.0023643698 | P51: 6.93 | Q51: 4
A52: 44166 | B52: =YEAR(A52) -> 2020 | C52: Complete | D52: 62016 | E52: -37293.5 | F52: =D52+E52 -> 24722.5 | G52: =IF(D52<0,"Yes","No") -> No | H52: =IF(D52<0,IF(E52>=-D52,"Yes","No"),"n/a") -> n/a | I52: =IF(D52<0,E52/-D52,"") | J52: 13981.75 | K52: =J52/J51-1 -> 0.078094217 | L52: 8418 | M52: 937713.45 | N52: 73.0536 | O52: =N52/N51-1 -> -0.010091018 | P52: 4.59 | Q52: 4
A53: 44197 | B53: =YEAR(A53) -> 2021 | C53: Complete | D53: 19473 | E53: -11970.5 | F53: =D53+E53 -> 7502.5 | G53: =IF(D53<0,"Yes","No") -> No | H53: =IF(D53<0,IF(E53>=-D53,"Yes","No"),"n/a") -> n/a | I53: =IF(D53<0,E53/-D53,"") | J53: 13634.6 | K53: =J53/J52-1 -> -0.024828795 | L53: 8023 | N53: 72.9519 | O53: =N53/N52-1 -> -0.0013921285 | P53: 4.06 | Q53: 4
A54: 44228 | B54: =YEAR(A54) -> 2021 | C54: Complete | D54: 25787 | E54: -16358.1 | F54: =D54+E54 -> 9428.9 | G54: =IF(D54<0,"Yes","No") -> No | H54: =IF(D54<0,IF(E54>=-D54,"Yes","No"),"n/a") -> n/a | I54: =IF(D54<0,E54/-D54,"") | J54: 14529.15 | K54: =J54/J53-1 -> 0.065608819 | L54: 7528 | N54: 73.0408 | O54: =N54/N53-1 -> 0.0012186112 | P54: 5.03 | Q54: 4
A55: 44256 | B55: =YEAR(A55) -> 2021 | C55: Complete | D55: 10482 | E55: 5204.4 | F55: =D55+E55 -> 15686.4 | G55: =IF(D55<0,"Yes","No") -> No | H55: =IF(D55<0,IF(E55>=-D55,"Yes","No"),"n/a") -> n/a | I55: =IF(D55<0,E55/-D55,"") | J55: 14690.7 | K55: =J55/J54-1 -> 0.011119026 | L55: 9182 | M55: 1002158.7 | N55: 73.5047 | O55: =N55/N54-1 -> 0.0063512448 | P55: 5.52 | Q55: 4
A56: 44287 | B56: =YEAR(A56) -> 2021 | C56: Complete | D56: -9659 | E56: 11088.6 | F56: =D56+E56 -> 1429.6 | G56: =IF(D56<0,"Yes","No") -> Yes | H56: =IF(D56<0,IF(E56>=-D56,"Yes","No"),"n/a") -> Yes | I56: =IF(D56<0,E56/-D56,"") -> 1.148007 | J56: 14631.1 | K56: =J56/J55-1 -> -0.0040569884 | L56: 8596 | N56: 74.0232 | O56: =N56/N55-1 -> 0.0070539707 | P56: 4.23 | Q56: 4
A57: 44317 | B57: =YEAR(A57) -> 2021 | C57: Complete | D57: -2954 | E57: 2067.2 | F57: =D57+E57 -> -886.8 | G57: =IF(D57<0,"Yes","No") -> Yes | H57: =IF(D57<0,IF(E57>=-D57,"Yes","No"),"n/a") -> No | I57: =IF(D57<0,E57/-D57,"") -> 0.69979689 | J57: 15582.8 | K57: =J57/J56-1 -> 0.065046374 | L57: 8819 | N57: 72.5211 | O57: =N57/N56-1 -> -0.020292287 | P57: 6.3 | Q57: 4
A58: 44348 | B58: =YEAR(A58) -> 2021 | C58: Complete | D58: 17215 | E58: 7043.5 | F58: =D58+E58 -> 24258.5 | G58: =IF(D58<0,"Yes","No") -> No | H58: =IF(D58<0,IF(E58>=-D58,"Yes","No"),"n/a") -> n/a | I58: =IF(D58<0,E58/-D58,"") | J58: 15721.5 | K58: =J58/J57-1 -> 0.0089008394 | L58: 9156 | M58: 1130457.7 | N58: 74.3456 | O58: =N58/N57-1 -> 0.025158195 | P58: 6.26 | Q58: 4
A59: 44378 | B59: =YEAR(A59) -> 2021 | C59: Complete | D59: -11308 | E59: 18893.9 | F59: =D59+E59 -> 7585.9 | G59: =IF(D59<0,"Yes","No") -> Yes | H59: =IF(D59<0,IF(E59>=-D59,"Yes","No"),"n/a") -> Yes | I59: =IF(D59<0,E59/-D59,"") -> 1.6708437 | J59: 15763.05 | K59: =J59/J58-1 -> 0.0026428776 | L59: 9609 | N59: 74.3871 | O59: =N59/N58-1 -> 0.00055820385 | P59: 5.59 | Q59: 4
A60: 44409 | B60: =YEAR(A60) -> 2021 | C60: Complete | D60: 2083 | E60: 6894.7 | F60: =D60+E60 -> 8977.7 | G60: =IF(D60<0,"Yes","No") -> No | H60: =IF(D60<0,IF(E60>=-D60,"Yes","No"),"n/a") -> n/a | I60: =IF(D60<0,E60/-D60,"") | J60: 17132.2 | K60: =J60/J59-1 -> 0.086858191 | L60: 9923 | N60: 73.1536 | O60: =N60/N59-1 -> -0.016582176 | P60: 5.3 | Q60: 4
A61: 44440 | B61: =YEAR(A61) -> 2021 | C61: Complete | D61: 13154 | E61: 5948.8 | F61: =D61+E61 -> 19102.8 | G61: =IF(D61<0,"Yes","No") -> No | H61: =IF(D61<0,IF(E61>=-D61,"Yes","No"),"n/a") -> n/a | I61: =IF(D61<0,E61/-D61,"") | J61: 17618.15 | K61: =J61/J60-1 -> 0.028364717 | L61: 10351 | M61: 1295884 | N61: 74.2551 | O61: =N61/N60-1 -> 0.015057359 | P61: 4.35 | Q61: 4
A62: 44470 | B62: =YEAR(A62) -> 2021 | C62: Complete | D62: -13550 | E62: 4471 | F62: =D62+E62 -> -9079 | G62: =IF(D62<0,"Yes","No") -> Yes | H62: =IF(D62<0,IF(E62>=-D62,"Yes","No"),"n/a") -> No | I62: =IF(D62<0,E62/-D62,"") -> 0.3299631 | J62: 17671.65 | K62: =J62/J61-1 -> 0.0030366412 | L62: 10519 | N62: 74.7858 | O62: =N62/N61-1 -> 0.0071469838 | P62: 4.48 | Q62: 4
A63: 44501 | B63: =YEAR(A63) -> 2021 | C63: Complete | D63: -5945 | E63: 30560.3 | F63: =D63+E63 -> 24615.3 | G63: =IF(D63<0,"Yes","No") -> Yes | H63: =IF(D63<0,IF(E63>=-D63,"Yes","No"),"n/a") -> Yes | I63: =IF(D63<0,E63/-D63,"") -> 5.1405046 | J63: 16983.2 | K63: =J63/J62-1 -> -0.038957879 | L63: 11005 | N63: 75.0885 | O63: =N63/N62-1 -> 0.0040475598 | P63: 4.91 | Q63: 4
A64: 44531 | B64: =YEAR(A64) -> 2021 | C64: Complete | D64: -19026 | E64: 31231 | F64: =D64+E64 -> 12205 | G64: =IF(D64<0,"Yes","No") -> Yes | H64: =IF(D64<0,IF(E64>=-D64,"Yes","No"),"n/a") -> Yes | I64: =IF(D64<0,E64/-D64,"") -> 1.6414906 | J64: 17354.05 | K64: =J64/J63-1 -> 0.021836285 | L64: 11305 | M64: 1346294.8 | N64: 74.3025 | O64: =N64/N63-1 -> -0.010467648 | P64: 5.66 | Q64: 4
A65: 44562 | B65: =YEAR(A65) -> 2022 | C65: Complete | D65: -33303 | E65: 21928.4 | F65: =D65+E65 -> -11374.6 | G65: =IF(D65<0,"Yes","No") -> Yes | H65: =IF(D65<0,IF(E65>=-D65,"Yes","No"),"n/a") -> No | I65: =IF(D65<0,E65/-D65,"") -> 0.65845119 | J65: 17339.85 | K65: =J65/J64-1 -> -0.0008182528 | L65: 11517 | N65: 74.9674 | O65: =N65/N64-1 -> 0.0089485549 | P65: 6.01 | Q65: 4
A66: 44593 | B66: =YEAR(A66) -> 2022 | C66: Complete | D66: -35592 | E66: 42084.1 | F66: =D66+E66 -> 6492.1 | G66: =IF(D66<0,"Yes","No") -> Yes | H66: =IF(D66<0,IF(E66>=-D66,"Yes","No"),"n/a") -> Yes | I66: =IF(D66<0,E66/-D66,"") -> 1.1824033 | J66: 16793.9 | K66: =J66/J65-1 -> -0.031485278 | L66: 11438 | N66: 75.4882 | O66: =N66/N65-1 -> 0.0069470196 | P66: 6.07 | Q66: 4
A67: 44621 | B67: =YEAR(A67) -> 2022 | C67: Complete | D67: -41123 | E67: 39677 | F67: =D67+E67 -> -1446 | G67: =IF(D67<0,"Yes","No") -> Yes | H67: =IF(D67<0,IF(E67>=-D67,"Yes","No"),"n/a") -> No | I67: =IF(D67<0,E67/-D67,"") -> 0.9648372 | J67: 17464.75 | K67: =J67/J66-1 -> 0.039946052 | L67: 12328 | M67: 1373728.6 | N67: 75.8071 | O67: =N67/N66-1 -> 0.0042245013 | P67: 6.95 | Q67: 4
A68: 44652 | B68: =YEAR(A68) -> 2022 | C68: Complete | D68: -17144 | E68: 30842.5 | F68: =D68+E68 -> 13698.5 | G68: =IF(D68<0,"Yes","No") -> Yes | H68: =IF(D68<0,IF(E68>=-D68,"Yes","No"),"n/a") -> Yes | I68: =IF(D68<0,E68/-D68,"") -> 1.7990259 | J68: 17102.55 | K68: =J68/J67-1 -> -0.020738917 | L68: 11863 | N68: 76.4242 | O68: =N68/N67-1 -> 0.0081403985 | P68: 7.79 | Q68: 4
A69: 44682 | B69: =YEAR(A69) -> 2022 | C69: Complete | D69: -39993 | E69: 50835.5 | F69: =D69+E69 -> 10842.5 | G69: =IF(D69<0,"Yes","No") -> Yes | H69: =IF(D69<0,IF(E69>=-D69,"Yes","No"),"n/a") -> Yes | I69: =IF(D69<0,E69/-D69,"") -> 1.2711099 | J69: 16584.55 | K69: =J69/J68-1 -> -0.030287881 | L69: 12286 | N69: 77.6641 | O69: =N69/N68-1 -> 0.016223919 | P69: 7.04 | Q69: 4.4
A70: 44713 | B70: =YEAR(A70) -> 2022 | C70: Complete | D70: -50203 | E70: 46599.2 | F70: =D70+E70 -> -3603.8 | G70: =IF(D70<0,"Yes","No") -> Yes | H70: =IF(D70<0,IF(E70>=-D70,"Yes","No"),"n/a") -> No | I70: =IF(D70<0,E70/-D70,"") -> 0.92821545 | J70: 15780.25 | K70: =J70/J69-1 -> -0.048496944 | L70: 12276 | N70: 78.9421 | O70: =N70/N69-1 -> 0.016455479 | P70: 7.01 | Q70: 4.9
A71: 44743 | B71: =YEAR(A71) -> 2022 | C71: Complete | D71: 4989 | E71: 10546 | F71: =D71+E71 -> 15535 | G71: =IF(D71<0,"Yes","No") -> No | H71: =IF(D71<0,IF(E71>=-D71,"Yes","No"),"n/a") -> n/a | I71: =IF(D71<0,E71/-D71,"") | J71: 17158.25 | K71: =J71/J70-1 -> 0.087324345 | L71: 12140 | N71: 79.4203 | O71: =N71/N70-1 -> 0.0060576042 | P71: 6.71 | Q71: 4.9
A72: 44774 | B72: =YEAR(A72) -> 2022 | C72: Complete | D72: 51204 | E72: -7068.6 | F72: =D72+E72 -> 44135.4 | G72: =IF(D72<0,"Yes","No") -> No | H72: =IF(D72<0,IF(E72>=-D72,"Yes","No"),"n/a") -> n/a | I72: =IF(D72<0,E72/-D72,"") | J72: 17759.3 | K72: =J72/J71-1 -> 0.035029796 | L72: 12693 | N72: 79.7194 | O72: =N72/N71-1 -> 0.0037660397 | P72: 7 | Q72: 5.4
A73: 44805 | B73: =YEAR(A73) -> 2022 | C73: Complete | D73: -7624 | E73: 14119.8 | F73: =D73+E73 -> 6495.8 | G73: =IF(D73<0,"Yes","No") -> Yes | H73: =IF(D73<0,IF(E73>=-D73,"Yes","No"),"n/a") -> Yes | I73: =IF(D73<0,E73/-D73,"") -> 1.8520199 | J73: 17094.35 | K73: =J73/J72-1 -> -0.037442354 | L73: 12976 | N73: 81.5522 | O73: =N73/N72-1 -> 0.02299064 | P73: 7.41 | Q73: 5.9
A74: 44835 | B74: =YEAR(A74) -> 2022 | C74: Complete | D74: -8 | E74: 9277 | F74: =D74+E74 -> 9269 | G74: =IF(D74<0,"Yes","No") -> Yes | H74: =IF(D74<0,IF(E74>=-D74,"Yes","No"),"n/a") -> Yes | I74: =IF(D74<0,E74/-D74,"") -> 1159.625 | J74: 18012.2 | K74: =J74/J73-1 -> 0.053693179 | L74: 13041 | N74: 82.3934 | O74: =N74/N73-1 -> 0.010314866 | P74: 6.77 | Q74: 5.9
A75: 44866 | B75: =YEAR(A75) -> 2022 | C75: Complete | D75: 36239 | E75: -6301.3 | F75: =D75+E75 -> 29937.7 | G75: =IF(D75<0,"Yes","No") -> No | H75: =IF(D75<0,IF(E75>=-D75,"Yes","No"),"n/a") -> n/a | I75: =IF(D75<0,E75/-D75,"") | J75: 18758.35 | K75: =J75/J74-1 -> 0.041424701 | L75: 13306 | N75: 81.597 | O75: =N75/N74-1 -> -0.0096658227 | P75: 5.88 | Q75: 5.9
A76: 44896 | B76: =YEAR(A76) -> 2022 | C76: Complete | D76: 11119 | E76: 24159.1 | F76: =D76+E76 -> 35278.1 | G76: =IF(D76<0,"Yes","No") -> No | H76: =IF(D76<0,IF(E76>=-D76,"Yes","No"),"n/a") -> n/a | I76: =IF(D76<0,E76/-D76,"") | J76: 18105.3 | K76: =J76/J75-1 -> -0.03481383 | L76: 13573 | M76: 1531893.6 | N76: 82.7862 | O76: =N76/N75-1 -> 0.014574065 | P76: 5.72 | Q76: 6.25
A77: 44927 | B77: =YEAR(A77) -> 2023 | C77: Complete | D77: -28852 | E77: 33411.8 | F77: =D77+E77 -> 4559.8 | G77: =IF(D77<0,"Yes","No") -> Yes | H77: =IF(D77<0,IF(E77>=-D77,"Yes","No"),"n/a") -> Yes | I77: =IF(D77<0,E77/-D77,"") -> 1.158041 | J77: 17662.15 | K77: =J77/J76-1 -> -0.024476258 | L77: 13856 | N77: 81.7387 | O77: =N77/N76-1 -> -0.012653075 | P77: 6.52 | Q77: 6.25
A78: 44958 | B78: =YEAR(A78) -> 2023 | C78: Complete | D78: -5294 | E78: 19239.3 | F78: =D78+E78 -> 13945.3 | G78: =IF(D78<0,"Yes","No") -> Yes | H78: =IF(D78<0,IF(E78>=-D78,"Yes","No"),"n/a") -> Yes | I78: =IF(D78<0,E78/-D78,"") -> 3.6341708 | J78: 17303.95 | K78: =J78/J77-1 -> -0.020280657 | L78: 13686 | N78: 82.6816 | O78: =N78/N77-1 -> 0.011535539 | P78: 6.44 | Q78: 6.5
A79: 44986 | B79: =YEAR(A79) -> 2023 | C79: Complete | D79: 7936 | E79: 30548.8 | F79: =D79+E79 -> 38484.8 | G79: =IF(D79<0,"Yes","No") -> No | H79: =IF(D79<0,IF(E79>=-D79,"Yes","No"),"n/a") -> n/a | I79: =IF(D79<0,E79/-D79,"") | J79: 17359.75 | K79: =J79/J78-1 -> 0.0032246973 | L79: 14276 | M79: 1523282.1 | N79: 82.2169 | O79: =N79/N78-1 -> -0.0056203557 | P79: 5.66 | Q79: 6.5
A80: 45017 | B80: =YEAR(A80) -> 2023 | C80: Complete | D80: 11631 | E80: 2216.6 | F80: =D80+E80 -> 13847.6 | G80: =IF(D80<0,"Yes","No") -> No | H80: =IF(D80<0,IF(E80>=-D80,"Yes","No"),"n/a") -> n/a | I80: =IF(D80<0,E80/-D80,"") | J80: 18065 | K80: =J80/J79-1 -> 0.040625585 | L80: 13728 | N80: 81.7829 | O80: =N80/N79-1 -> -0.0052787201 | P80: 4.7 | Q80: 6.5
A81: 45047 | B81: =YEAR(A81) -> 2023 | C81: Complete | D81: 43838 | E81: -3306.4 | F81: =D81+E81 -> 40531.6 | G81: =IF(D81<0,"Yes","No") -> No | H81: =IF(D81<0,IF(E81>=-D81,"Yes","No"),"n/a") -> n/a | I81: =IF(D81<0,E81/-D81,"") | J81: 18534.4 | K81: =J81/J80-1 -> 0.025983947 | L81: 14749 | N81: 82.6773 | O81: =N81/N80-1 -> 0.010936272 | P81: 4.31 | Q81: 6.5
A82: 45078 | B82: =YEAR(A82) -> 2023 | C82: Complete | D82: 47148 | E82: 4458.2 | F82: =D82+E82 -> 51606.2 | G82: =IF(D82<0,"Yes","No") -> No | H82: =IF(D82<0,IF(E82>=-D82,"Yes","No"),"n/a") -> n/a | I82: =IF(D82<0,E82/-D82,"") | J82: 19189.05 | K82: =J82/J81-1 -> 0.035320809 | L82: 14734 | M82: 1747576.7 | N82: 82.0428 | O82: =N82/N81-1 -> -0.0076744161 | P82: 4.87 | Q82: 6.5
A83: 45108 | B83: =YEAR(A83) -> 2023 | C83: Complete | D83: 46618 | E83: -2697.7 | F83: =D83+E83 -> 43920.3 | G83: =IF(D83<0,"Yes","No") -> No | H83: =IF(D83<0,IF(E83>=-D83,"Yes","No"),"n/a") -> n/a | I83: =IF(D83<0,E83/-D83,"") | J83: 19753.8 | K83: =J83/J82-1 -> 0.029430847 | L83: 15245 | N83: 82.2481 | O83: =N83/N82-1 -> 0.0025023524 | P83: 7.44 | Q83: 6.5
A84: 45139 | B84: =YEAR(A84) -> 2023 | C84: Complete | D84: 12262 | E84: 25017 | F84: =D84+E84 -> 37279 | G84: =IF(D84<0,"Yes","No") -> No | H84: =IF(D84<0,IF(E84>=-D84,"Yes","No"),"n/a") -> n/a | I84: =IF(D84<0,E84/-D84,"") | J84: 19253.8 | K84: =J84/J83-1 -> -0.025311586 | L84: 15814 | N84: 82.6784 | O84: =N84/N83-1 -> 0.0052317318 | P84: 6.83 | Q84: 6.5
A85: 45170 | B85: =YEAR(A85) -> 2023 | C85: Complete | D85: -14768 | E85: 20312.6 | F85: =D85+E85 -> 5544.6 | G85: =IF(D85<0,"Yes","No") -> Yes | H85: =IF(D85<0,IF(E85>=-D85,"Yes","No"),"n/a") -> Yes | I85: =IF(D85<0,E85/-D85,"") -> 1.3754469 | J85: 19638.3 | K85: =J85/J84-1 -> 0.019970084 | L85: 16042 | M85: 1912017.3 | N85: 83.058 | O85: =N85/N84-1 -> 0.0045912838 | P85: 5.02 | Q85: 6.5
A86: 45200 | B86: =YEAR(A86) -> 2023 | C86: Complete | D86: -24548 | E86: 28254 | F86: =D86+E86 -> 3706 | G86: =IF(D86<0,"Yes","No") -> Yes | H86: =IF(D86<0,IF(E86>=-D86,"Yes","No"),"n/a") -> Yes | I86: =IF(D86<0,E86/-D86,"") -> 1.1509695 | J86: 19079.6 | K86: =J86/J85-1 -> -0.028449509 | L86: 16928 | N86: 83.2692 | O86: =N86/N85-1 -> 0.0025428014 | P86: 4.87 | Q86: 6.5
A87: 45231 | B87: =YEAR(A87) -> 2023 | C87: Complete | D87: 9001 | E87: 14253.7 | F87: =D87+E87 -> 23254.7 | G87: =IF(D87<0,"Yes","No") -> No | H87: =IF(D87<0,IF(E87>=-D87,"Yes","No"),"n/a") -> n/a | I87: =IF(D87<0,E87/-D87,"") | J87: 20133.15 | K87: =J87/J86-1 -> 0.055218663 | L87: 17073 | N87: 83.35 | O87: =N87/N86-1 -> 0.00097034678 | P87: 5.55 | Q87: 6.5
A88: 45261 | B88: =YEAR(A88) -> 2023 | C88: Complete | D88: 66135 | E88: 12942.2 | F88: =D88+E88 -> 79077.2 | G88: =IF(D88<0,"Yes","No") -> No | H88: =IF(D88<0,IF(E88>=-D88,"Yes","No"),"n/a") -> n/a | I88: =IF(D88<0,E88/-D88,"") | J88: 21731.4 | K88: =J88/J87-1 -> 0.079384001 | L88: 17610 | M88: 2183650.6 | N88: 83.1164 | O88: =N88/N87-1 -> -0.0028026395 | P88: 5.69 | Q88: 6.5
A89: 45292 | B89: =YEAR(A89) -> 2024 | C89: Complete | D89: -25744 | E89: 26743.6 | F89: =D89+E89 -> 999.6 | G89: =IF(D89<0,"Yes","No") -> Yes | H89: =IF(D89<0,IF(E89>=-D89,"Yes","No"),"n/a") -> Yes | I89: =IF(D89<0,E89/-D89,"") -> 1.0388285 | J89: 21725.7 | K89: =J89/J88-1 -> -0.00026229327 | L89: 18838 | N89: 83.0805 | O89: =N89/N88-1 -> -0.00043192439 | P89: 5.1 | Q89: 6.5
A90: 45323 | B90: =YEAR(A90) -> 2024 | C90: Complete | D90: 1539 | E90: 25379.3 | F90: =D90+E90 -> 26918.3 | G90: =IF(D90<0,"Yes","No") -> No | H90: =IF(D90<0,IF(E90>=-D90,"Yes","No"),"n/a") -> n/a | I90: =IF(D90<0,E90/-D90,"") | J90: 21982.8 | K90: =J90/J89-1 -> 0.011833911 | L90: 19187 | N90: 82.9246 | O90: =N90/N89-1 -> -0.0018764933 | P90: 5.09 | Q90: 6.5
A91: 45352 | B91: =YEAR(A91) -> 2024 | C91: Complete | D91: 35098 | E91: 56311.6 | F91: =D91+E91 -> 91409.6 | G91: =IF(D91<0,"Yes","No") -> No | H91: =IF(D91<0,IF(E91>=-D91,"Yes","No"),"n/a") -> n/a | I91: =IF(D91<0,E91/-D91,"") | J91: 22326.9 | K91: =J91/J90-1 -> 0.015653147 | L91: 19271 | M91: 2353037.2 | N91: 83.3739 | O91: =N91/N90-1 -> 0.0054181751 | P91: 4.85 | Q91: 6.5
A92: 45383 | B92: =YEAR(A92) -> 2024 | C92: Complete | D92: -8671 | E92: 44186.3 | F92: =D92+E92 -> 35515.3 | G92: =IF(D92<0,"Yes","No") -> Yes | H92: =IF(D92<0,IF(E92>=-D92,"Yes","No"),"n/a") -> Yes | I92: =IF(D92<0,E92/-D92,"") -> 5.0958713 | J92: 22604.85 | K92: =J92/J91-1 -> 0.012449108 | L92: 20371 | N92: 83.5187 | O92: =N92/N91-1 -> 0.0017367545 | P92: 4.83 | Q92: 6.5
A93: 45413 | B93: =YEAR(A93) -> 2024 | C93: Complete | D93: -25586 | E93: 55733 | F93: =D93+E93 -> 30147 | G93: =IF(D93<0,"Yes","No") -> Yes | H93: =IF(D93<0,IF(E93>=-D93,"Yes","No"),"n/a") -> Yes | I93: =IF(D93<0,E93/-D93,"") -> 2.1782615 | J93: 22530.7 | K93: =J93/J92-1 -> -0.0032802695 | L93: 20904 | N93: 83.2988 | O93: =N93/N92-1 -> -0.0026329433 | P93: 4.8 | Q93: 6.5
A94: 45444 | B94: =YEAR(A94) -> 2024 | C94: Complete | D94: 26565 | E94: 28633.2 | F94: =D94+E94 -> 55198.2 | G94: =IF(D94<0,"Yes","No") -> No | H94: =IF(D94<0,IF(E94>=-D94,"Yes","No"),"n/a") -> n/a | I94: =IF(D94<0,E94/-D94,"") | J94: 24010.6 | K94: =J94/J93-1 -> 0.065683712 | L94: 21262 | M94: 2772493.7 | N94: 83.4534 | O94: =N94/N93-1 -> 0.0018559691 | P94: 5.08 | Q94: 6.5
A95: 45474 | B95: =YEAR(A95) -> 2024 | C95: Complete | D95: 32365 | E95: 23486 | F95: =D95+E95 -> 55851 | G95: =IF(D95<0,"Yes","No") -> No | H95: =IF(D95<0,IF(E95>=-D95,"Yes","No"),"n/a") -> n/a | I95: =IF(D95<0,E95/-D95,"") | J95: 24951.15 | K95: =J95/J94-1 -> 0.039172282 | L95: 23332 | N95: 83.744 | O95: =N95/N94-1 -> 0.0034821829 | P95: 3.6 | Q95: 6.5
A96: 45505 | B96: =YEAR(A96) -> 2024 | C96: Complete | D96: 7320 | E96: 48278.6 | F96: =D96+E96 -> 55598.6 | G96: =IF(D96<0,"Yes","No") -> No | H96: =IF(D96<0,IF(E96>=-D96,"Yes","No"),"n/a") -> n/a | I96: =IF(D96<0,E96/-D96,"") | J96: 25235.9 | K96: =J96/J95-1 -> 0.0114123 | L96: 23547 | N96: 83.8709 | O96: =N96/N95-1 -> 0.0015153324 | P96: 3.65 | Q96: 6.5
A97: 45536 | B97: =YEAR(A97) -> 2024 | C97: Complete | D97: 57724 | E97: 31860.2 | F97: =D97+E97 -> 89584.2 | G97: =IF(D97<0,"Yes","No") -> No | H97: =IF(D97<0,IF(E97>=-D97,"Yes","No"),"n/a") -> n/a | I97: =IF(D97<0,E97/-D97,"") | J97: 25810.85 | K97: =J97/J96-1 -> 0.022783019 | L97: 24509 | M97: 3154806.2 | N97: 83.7888 | O97: =N97/N96-1 -> -0.00097888541 | P97: 5.49 | Q97: 6.5
A98: 45566 | B98: =YEAR(A98) -> 2024 | C98: Complete | D98: -94017 | E98: 107254.7 | F98: =D98+E98 -> 13237.7 | G98: =IF(D98<0,"Yes","No") -> Yes | H98: =IF(D98<0,IF(E98>=-D98,"Yes","No"),"n/a") -> Yes | I98: =IF(D98<0,E98/-D98,"") -> 1.1408011 | J98: 24205.35 | K98: =J98/J97-1 -> -0.062202523 | L98: 25323 | N98: 84.0886 | O98: =N98/N97-1 -> 0.0035780438 | P98: 6.21 | Q98: 6.5
A99: 45597 | B99: =YEAR(A99) -> 2024 | C99: Complete | D99: -21612 | E99: 44483.9 | F99: =D99+E99 -> 22871.9 | G99: =IF(D99<0,"Yes","No") -> Yes | H99: =IF(D99<0,IF(E99>=-D99,"Yes","No"),"n/a") -> Yes | I99: =IF(D99<0,E99/-D99,"") -> 2.0582963 | J99: 24131.1 | K99: =J99/J98-1 -> -0.0030675037 | L99: 25320 | N99: 84.4971 | O99: =N99/N98-1 -> 0.0048579712 | P99: 5.48 | Q99: 6.5
A100: 45627 | B100: =YEAR(A100) -> 2024 | C100: Complete | D100: 15446 | E100: 34194.7 | F100: =D100+E100 -> 49640.7 | G100: =IF(D100<0,"Yes","No") -> No | H100: =IF(D100<0,IF(E100>=-D100,"Yes","No"),"n/a") -> n/a | I100: =IF(D100<0,E100/-D100,"") | J100: 23644.8 | K100: =J100/J99-1 -> -0.020152417 | L100: 26459 | M100: 3103797.7 | N100: 85.6232 | O100: =N100/N99-1 -> 0.013327085 | P100: 5.22 | Q100: 6.5
A101: 45658 | B101: =YEAR(A101) -> 2025 | C101: Complete | D101: -78027 | E101: 86591.8 | F101: =D101+E101 -> 8564.8 | G101: =IF(D101<0,"Yes","No") -> Yes | H101: =IF(D101<0,IF(E101>=-D101,"Yes","No"),"n/a") -> Yes | I101: =IF(D101<0,E101/-D101,"") -> 1.1097671 | J101: 23508.4 | K101: =J101/J100-1 -> -0.0057687102 | L101: 26400 | N101: 86.6414 | O101: =N101/N100-1 -> 0.011891637 | P101: 4.26 | Q101: 6.5
...

Sheet Method & Sources
A1: Method, sources and status
A3: Objective
A4: Question | B4: Whether domestic institutional buying has become large enough to absorb foreign portfolio selling in Indian equities, and how flows relate to Nifty returns, SIP growth and macro conditions.
A6: Definitions
A7: Flow sign | B7: Positive = net buying, negative = net selling. Monthly flow is the net equity position for the calendar month, in ₹ crore.
A8: Fully offset | B8: A month where FPI net flow is negative and DII net flow is at least equal to its absolute value.
A9: Nifty return | B9: Month-end close divided by prior month-end close, minus one.
A10: USD/INR change | B10: Month-end rate divided by prior month-end rate, minus one. A positive value is rupee depreciation.
A11: Sample | B11: 117 complete months, January 2017 to September 2026. October 2026 is partial (to 23 Oct) and excluded from all statistics.
A12: Missing data | B12: Left blank, never set to zero. Repo rate and USD/INR begin in October 2017; Nifty return begins in February 2017; AUM is available at quarter-ends only.
A14: Data sources
A15: FPI net equity flow | B15: NSDL monthly reports (depository basis).
A16: DII net equity flow | B16: Trendlyne monthly table, transcribed manually. July 2026 checked against published figures.
A17: Nifty 50 | B17: NSE daily index files, aggregated to month-end.
A18: SIP contributions | B18: AMFI monthly SIP data. December 2025 and January 2026 both report ₹31,002 crore, confirmed against AMFI.
A19: Equity mutual fund AUM | B19: AMFI quarterly category-wise report; sum of equity-oriented category totals.
A20: Repo rate, USD/INR, CPI | B20: Monthly macro indicators file compiled from RBI and MoSPI releases.
A22: Status and limitations
A23: Flow series | B23: FPI (depository basis) and DII (exchange basis) come from different sources and may not be strictly comparable. For July 2026 the FPI figure here is +₹20,200 crore against about -₹5,779 crore in the exchange cash-market data.
A24: Next step | B24: Rebuild both series from the NSE combined FII/FPI and DII cash-market report (NSE, BSE and MSEI), aggregate to months, and rerun the offset, stress-test and correlation tabs. Offset rates and flow correlations should be treated as preliminary until then.
A25: Interpretation | B25: All results are descriptive associations. No causal claim is made.
A26: Not used | B26: AMFI folio counts are excluded because category folios overlap and do not represent unique investors.
A28: Workbook map
A29: Summary | B29: Headline figures and charts.
A30: Findings | B30: Seven findings with result, reading and limitation.
A31: Offset Analysis | B31: Offset rates, regime returns and the ten-month stress test.
A32: Correlations | B32: Flow and macro correlations with robustness checks.
A33: Annual Summary | B33: Year-by-year flows, offsets and SIP.
A34: Monthly Data | B34: Source data and calculated columns that drive every other tab.
